measure_horseshoe_bat_calls/__init__.py
measure_horseshoe_bat_calls/measure_a_horseshoe_bat_call.py
measure_horseshoe_bat_calls/segment_horseshoebat_call.py
measure_horseshoe_bat_calls/signal_processing.py
measure_horseshoe_bat_calls/tests.py
measure_horseshoe_bat_calls/view_horseshoebat_call.py
measure_horseshoe_bat_calls/data/__init__.py
measure_horseshoe_bat_calls/data/matching_annotaudio_Aditya_2018-08-17_23_115.WAV
measure_horseshoe_bat_calls/data/matching_annotaudio_Aditya_2018-08-17_23_14.WAV
measure_horseshoe_bat_calls/data/matching_annotaudio_Aditya_2018-08-17_23_141.WAV
measure_horseshoe_bat_calls/data/matching_annotaudio_Aditya_2018-08-17_23_157.WAV
measure_horseshoe_bat_calls/data/matching_annotaudio_Aditya_2018-08-17_23_173.WAV
measure_horseshoe_bat_calls/data/matching_annotaudio_Aditya_2018-08-17_23_196.WAV
measure_horseshoe_bat_calls/data/matching_annotaudio_Aditya_2018-08-17_23_24.WAV
measure_horseshoe_bat_calls/data/matching_annotaudio_Aditya_2018-08-17_23_56.WAV
measure_horseshoe_bat_calls/data/matching_annotaudio_Aditya_2018-08-17_23_65.WAV
measure_horseshoe_bat_calls/data/matching_annotaudio_Aditya_2018-08-17_23_70.WAV
measure_horseshoe_bat_calls/data/matching_annotaudio_Aditya_2018-08-17_34_1.WAV
measure_horseshoe_bat_calls/data/matching_annotaudio_Aditya_2018-08-17_34_111.WAV
measure_horseshoe_bat_calls/data/matching_annotaudio_Aditya_2018-08-17_34_12.WAV
measure_horseshoe_bat_calls/data/matching_annotaudio_Aditya_2018-08-17_34_120.WAV
measure_horseshoe_bat_calls/data/matching_annotaudio_Aditya_2018-08-17_34_132.WAV
measure_horseshoe_bat_calls/data/matching_annotaudio_Aditya_2018-08-17_34_133.WAV
measure_horseshoe_bat_calls/data/matching_annotaudio_Aditya_2018-08-17_34_134.WAV
measure_horseshoe_bat_calls/data/matching_annotaudio_Aditya_2018-08-17_34_142.WAV
measure_horseshoe_bat_calls/data/matching_annotaudio_Aditya_2018-08-17_34_144.WAV
measure_horseshoe_bat_calls/data/matching_annotaudio_Aditya_2018-08-17_34_145.WAV
measure_horseshoe_bat_calls-1.0.0.dist-info/LICENSE
measure_horseshoe_bat_calls-1.0.0.dist-info/METADATA
measure_horseshoe_bat_calls-1.0.0.dist-info/WHEEL
measure_horseshoe_bat_calls-1.0.0.dist-info/top_level.txt
measure_horseshoe_bat_calls-1.0.0.dist-info/RECORD
