Metadata-Version: 2.1
Name: measure-horseshoe-bat-calls
Version: 1.0.0
Summary: Measure single Cf bat calls, or sounds like it
Home-page: https://github.com/thejasvibr/measure_horseshoe_bat_calls.git
Author: Thejasvi Beleyur
Author-email: thejasvib@gmail.com
License: MIT
Platform: UNKNOWN
Classifier: Intended Audience :: Science/Research
Classifier: Topic :: Multimedia :: Sound/Audio :: Analysis
Classifier: Topic :: Multimedia :: Sound/Audio
Classifier: Programming Language :: Python :: 2.7
Classifier: Programming Language :: Python :: 3
Requires-Dist: numpy (>1.15)
Requires-Dist: pandas
Requires-Dist: soundfile
Requires-Dist: peakutils
Requires-Dist: scipy
Requires-Dist: matplotlib
Requires-Dist: PyWavelets
